async_boto/__init__.py
async_boto/clients/__init__.py
async_boto/clients/dynamodb.py
async_boto/clients/lambda_.py
async_boto/clients/sqs.py
async_boto/clients/timestream_query.py
async_boto/clients/timestream_write.py
async_boto/core/__init__.py
async_boto/core/aws_sig_v4_headers.py
async_boto/core/base_client.py
async_boto/core/errors.py
async_boto/core/profile_manager.py
async_boto/core/response.py
async_boto/core/session.py
async_boto/utils/__init__.py
async_boto/utils/batching.py
async_boto/utils/dynamo_conversion.py
async_boto/utils/generate_param_tuple.py
async_boto/utils/json_dumps.py
async_boto/utils/paginate.py
async_boto/utils/unpack_lists.py
async_boto/validation/__init__.py
async_boto/validation/dynamodb/__init__.py
async_boto/validation/dynamodb/batch_execute_statement.py
async_boto/validation/dynamodb/batch_get_item.py
async_boto/validation/dynamodb/batch_write_items.py
async_boto/validation/dynamodb/create_backup.py
async_boto/validation/dynamodb/create_global_table.py
async_boto/validation/dynamodb/create_table.py
async_boto/validation/dynamodb/delete_backup.py
async_boto/validation/dynamodb/delete_item.py
async_boto/validation/dynamodb/delete_resource_policy.py
async_boto/validation/dynamodb/delete_table.py
async_boto/validation/dynamodb/describe_backup.py
async_boto/validation/dynamodb/describe_continous_backups.py
async_boto/validation/dynamodb/describe_contributor_insights.py
async_boto/validation/dynamodb/describe_enpoints.py
async_boto/validation/dynamodb/describe_export.py
async_boto/validation/dynamodb/describe_global_table.py
async_boto/validation/dynamodb/describe_global_table_settings.py
async_boto/validation/dynamodb/describe_import.py
async_boto/validation/dynamodb/describe_kinesis_streaming_destination.py
async_boto/validation/dynamodb/describe_limits.py
async_boto/validation/dynamodb/describe_table.py
async_boto/validation/dynamodb/describe_table_replica_auto_scaling.py
async_boto/validation/dynamodb/describe_time_to_live.py
asyncboto-1.2.0.dist-info/METADATA
asyncboto-1.2.0.dist-info/WHEEL
asyncboto-1.2.0.dist-info/top_level.txt
asyncboto-1.2.0.dist-info/RECORD
