Metadata-Version: 2.4
Name: AsyncBoto
Version: 1.2.0
Summary: Python package to asyncronous interact with AWS
Author-email: Christopher Müller <christopher.m4120@gmail.com>
Project-URL: Homepage, https://github.com/SpielerNogard/AsyncBoto
Project-URL: Documentation, https://spielernogard.github.io/AsyncBoto/
Requires-Python: >=3.11
Requires-Dist: pydantic<3.0.0,>=2.0.0
Requires-Dist: aiohttp<4.0.0,>=3.8.5
Requires-Dist: tenacity
Requires-Dist: boto3
